play2048/__init__.py
play2048/custom.py
play2048/enums.py
play2048/game.py
play2048-6.0.dist-info/LICENSE
play2048-6.0.dist-info/METADATA
play2048-6.0.dist-info/WHEEL
play2048-6.0.dist-info/top_level.txt
play2048-6.0.dist-info/RECORD
