Metadata-Version: 2.1
Name: play2048
Version: 6.0
Summary: just 2048 game lib
Home-page: https://github.com/5-23/play2048
Author: 5-23
Author-email: rustacean@5-23.dev
License: MIT
Keywords: 5-23,2048,game,play2048,2048play
Classifier: Programming Language :: Python :: 3
Classifier: License :: OSI Approved :: MIT License
Classifier: Operating System :: OS Independent
Requires-Python: >=3.6
License-File: LICENSE
Requires-Dist: easy-pil
